Metadata-Version: 1.0
Name: package-test-BJL
Version: 0.1
Summary: This package is a test
Home-page: http://github.com/bjlemaire/package_test_BJL
Author: Baptiste J Lemaire
Author-email: blemaire@g.harvard.edu
License: Harvard
Platform: UNKNOWN
